pfcf/__init__.c
pfcf/__init__.cpython-37m-x86_64-linux-gnu.so
pfcf/init.c
pfcf/init.cpython-37m-x86_64-linux-gnu.so
pfcf/pfcf.c
pfcf/pfcf.cpython-37m-x86_64-linux-gnu.so
pfcf/account/__init__.c
pfcf/account/__init__.cpython-37m-x86_64-linux-gnu.so
pfcf/account/daccount.c
pfcf/account/daccount.cpython-37m-x86_64-linux-gnu.so
pfcf/account/ddata.c
pfcf/account/ddata.cpython-37m-x86_64-linux-gnu.so
pfcf/account/faccount.c
pfcf/account/faccount.cpython-37m-x86_64-linux-gnu.so
pfcf/account/fdata.c
pfcf/account/fdata.cpython-37m-x86_64-linux-gnu.so
pfcf/cgcrypt/__init__.c
pfcf/cgcrypt/__init__.cpython-37m-x86_64-linux-gnu.so
pfcf/cgcrypt/cgcrypt.c
pfcf/cgcrypt/cgcrypt.cpython-37m-x86_64-linux-gnu.so
pfcf/cgcrypt/cgcryptcore.c
pfcf/cgcrypt/cgcryptcore.cpython-37m-x86_64-linux-gnu.so
pfcf/cgcrypt/error_code.c
pfcf/cgcrypt/error_code.cpython-37m-x86_64-linux-gnu.so
pfcf/cgcrypt/flag.c
pfcf/cgcrypt/flag.cpython-37m-x86_64-linux-gnu.so
pfcf/core/__init__.c
pfcf/core/__init__.cpython-37m-x86_64-linux-gnu.so
pfcf/core/common.c
pfcf/core/common.cpython-37m-x86_64-linux-gnu.so
pfcf/core/error.c
pfcf/core/error.cpython-37m-x86_64-linux-gnu.so
pfcf/core/httpclient.c
pfcf/core/httpclient.cpython-37m-x86_64-linux-gnu.so
pfcf/core/limiter.c
pfcf/core/limiter.cpython-37m-x86_64-linux-gnu.so
pfcf/core/logger.c
pfcf/core/logger.cpython-37m-x86_64-linux-gnu.so
pfcf/core/sign.c
pfcf/core/sign.cpython-37m-x86_64-linux-gnu.so
pfcf/core/tcpclient.c
pfcf/core/tcpclient.cpython-37m-x86_64-linux-gnu.so
pfcf/core/tcpspec.c
pfcf/core/tcpspec.cpython-37m-x86_64-linux-gnu.so
pfcf/product/__init__.c
pfcf/product/__init__.cpython-37m-x86_64-linux-gnu.so
pfcf/product/domesticcontract.c
pfcf/product/domesticcontract.cpython-37m-x86_64-linux-gnu.so
pfcf/product/domesticproduct.c
pfcf/product/domesticproduct.cpython-37m-x86_64-linux-gnu.so
pfcf/product/exchange.c
pfcf/product/exchange.cpython-37m-x86_64-linux-gnu.so
pfcf/product/foreigncontract.c
samanthapantest-1.0.0.113.dist-info/METADATA
samanthapantest-1.0.0.113.dist-info/WHEEL
samanthapantest-1.0.0.113.dist-info/top_level.txt
samanthapantest-1.0.0.113.dist-info/RECORD
