Metadata-Version: 2.1
Name: samanthapantest
Version: 1.0.0.113
Summary: pfcf api
Home-page: UNKNOWN
License: UNKNOWN
Platform: UNKNOWN
Classifier: Programming Language :: Python :: 3
Classifier: Programming Language :: Python :: 3.7
Classifier: Programming Language :: Python :: 3.8
Classifier: Programming Language :: Python :: 3.9
Classifier: Programming Language :: Python :: 3.10
Classifier: Programming Language :: Python :: 3.11
Classifier: Programming Language :: Python :: 3.12
Classifier: License :: OSI Approved :: MIT License
Classifier: Operating System :: OS Independent
Requires-Python: >=3.7, <4
Requires-Dist: bitarray >=2.3.4
Requires-Dist: requests
Requires-Dist: cryptography
Requires-Dist: cython
Requires-Dist: numpy
